{
    "columns": [
        {
            "ColumnName": "user_id",
            "ColumnType": "string",
            "PK": true
        },
        {
            "ColumnName": "cb_service_account",
            "ColumnType": "bool",
            "PK": false
        },
        {
            "ColumnName": "cb_ttl_override",
            "ColumnType": "int",
            "PK": false
        },
        {
            "ColumnName": "cb_token",
            "ColumnType": "string",
            "PK": false
        }
    ]
}